README.md
setup.py
aiopaypal/__init__.py
aiopaypal.egg-info/PKG-INFO
aiopaypal.egg-info/SOURCES.txt
aiopaypal.egg-info/dependency_links.txt
aiopaypal.egg-info/requires.txt
aiopaypal.egg-info/top_level.txt