Metadata-Version: 2.1
Name: aiopaypal
Version: 0.1.3
Summary: Async Paypal client
Home-page: https://github.com/omarryhan/aiopaypal
Author: Omar Ryhan
Author-email: omarryhan@gmail.com
License: GNU
Platform: UNKNOWN
Classifier: Programming Language :: Python :: 3.7
Classifier: Operating System :: OS Independent
